cowboy/__init__.py
cowboy/browser.py
cowboy/cli.py
cowboy/config.py
cowboy/exceptions.py
cowboy/logger.py
cowboy/utils.py
cowboy/api_cmds/__init__.py
cowboy/api_cmds/augment.py
cowboy/api_cmds/build_mapping.py
cowboy/api_cmds/experiment.py
cowboy/api_cmds/get_tms.py
cowboy/api_cmds/register.py
cowboy/api_cmds/remote_head.py
cowboy/build/asset-manifest.json
cowboy/build/favicon.ico
cowboy/build/index.html
cowboy/build/logo192.png
cowboy/build/logo512.png
cowboy/build/manifest.json
cowboy/build/robots.txt
cowboy/build/static/css/main.36db2714.css
cowboy/build/static/css/main.36db2714.css.map
cowboy/build/static/js/6453.c0b6ed50.chunk.js
cowboy/build/static/js/6453.c0b6ed50.chunk.js.map
cowboy/build/static/js/main.b0026056.js
cowboy/build/static/js/main.b0026056.js.LICENSE.txt
cowboy/build/static/js/main.b0026056.js.map
cowboy/build/static/js/react-syntax-highlighter_languages_refractor_abap.c2ac9226.chunk.js
cowboy/build/static/js/react-syntax-highlighter_languages_refractor_abap.c2ac9226.chunk.js.map
cowboy/build/static/js/react-syntax-highlighter_languages_refractor_abnf.9e2fd725.chunk.js
cowboy/build/static/js/react-syntax-highlighter_languages_refractor_abnf.9e2fd725.chunk.js.map
cowboy/build/static/js/react-syntax-highlighter_languages_refractor_actionscript.be80ba83.chunk.js
cowboy/build/static/js/react-syntax-highlighter_languages_refractor_actionscript.be80ba83.chunk.js.map
cowboy/build/static/js/react-syntax-highlighter_languages_refractor_ada.3cc3e845.chunk.js
cowboy/build/static/js/react-syntax-highlighter_languages_refractor_ada.3cc3e845.chunk.js.map
cowboy/build/static/js/react-syntax-highlighter_languages_refractor_agda.9beafba1.chunk.js
cowboy/build/static/js/react-syntax-highlighter_languages_refractor_agda.9beafba1.chunk.js.map
cowboy/build/static/js/react-syntax-highlighter_languages_refractor_al.a2759e52.chunk.js
cowboy/build/static/js/react-syntax-highlighter_languages_refractor_al.a2759e52.chunk.js.map
cowboy_client-0.7.5.dist-info/METADATA
cowboy_client-0.7.5.dist-info/WHEEL
cowboy_client-0.7.5.dist-info/entry_points.txt
cowboy_client-0.7.5.dist-info/top_level.txt
cowboy_client-0.7.5.dist-info/RECORD
