Metadata-Version: 2.1
Name: cowboy-client
Version: 0.7.5
Summary: Cowboy Client Interface
Author: John Peng
Author-email: kongyijipeng@gmail.com
Requires-Python: >=3.8
Requires-Dist: click
Requires-Dist: pyyaml
Requires-Dist: pydantic ==2.7.4
Requires-Dist: gitpython ==3.0.6
Requires-Dist: requests
Requires-Dist: platformdirs
Requires-Dist: pytz
